setup.py
spotifi/__init__.py
spotifi.egg-info/PKG-INFO
spotifi.egg-info/SOURCES.txt
spotifi.egg-info/dependency_links.txt
spotifi.egg-info/top_level.txt