Metadata-Version: 2.4
Name: spotifi
Version: 0.1.1
Summary: A python package that is spotifi
Author: fswair
Classifier: Programming Language :: Python :: 3
Classifier: License :: OSI Approved :: MIT License
Classifier: Operating System :: OS Independent
Dynamic: author
Dynamic: classifier
Dynamic: summary
